easyauth/__init__.py
easyauth/api.py
easyauth/client.py
easyauth/db.py
easyauth/exceptions.py
easyauth/frontend.py
easyauth/models.py
easyauth/pages.py
easyauth/router.py
easyauth/server.py
easyauth/utils.py
easy_auth-2.0.3.dist-info/LICENSE.MD
easy_auth-2.0.3.dist-info/METADATA
easy_auth-2.0.3.dist-info/WHEEL
easy_auth-2.0.3.dist-info/top_level.txt
easy_auth-2.0.3.dist-info/RECORD
